LICENSE.txt
MANIFEST.in
README.rst
setup.cfg
setup.py
gaerpytz.egg-info/PKG-INFO
gaerpytz.egg-info/SOURCES.txt
gaerpytz.egg-info/dependency_links.txt
gaerpytz.egg-info/not-zip-safe
gaerpytz.egg-info/top_level.txt
pytz/__init__.py
pytz/exceptions.py
pytz/lazy.py
pytz/reference.py
pytz/tzfile.py
pytz/tzinfo.py
pytz/zoneinfo.zip