Metadata-Version: 1.1
Name: gaerpytz
Version: 2018.9
Summary: gaerpytz is like gaepytz (a version of pytz that works well on Google App Engine) but automated so zoneinfo is up-to-date.
Home-page: https://gaerpytz.appspot.com/
Author: gaerpytz
Author-email: support@gaerpytz.appspotmail.com
License: MIT
Keywords: timezone tzinfo datetime olson time
Platform: any
Classifier: Development Status :: 5 - Production/Stable
Classifier: Intended Audience :: Developers
Classifier: License :: OSI Approved :: MIT License
Classifier: Natural Language :: English
Classifier: Operating System :: OS Independent
Classifier: Programming Language :: Python
Classifier: Programming Language :: Python :: 2
Classifier: Programming Language :: Python :: 3
Classifier: Topic :: Software Development :: Libraries :: Python Modules
